{
    "mipEra": "cmip6", 
    "institute": "csiro", 
    "seedingSource": "Spreadsheet", 
    "sourceID": "access-esm1-5", 
    "topic": "ocnbgchem", 
    "content": {
        "cmip6.ocnbgchem.tracers.name": {
            "values": [
                "Phosphate, phytoplankton, zooplankton, detritus, oxygen, carbonate, dissolved inorganic carbon, natural dissolved inorganic carbon, alkalinity, iron."
            ]
        }, 
        "cmip6.ocnbgchem.tracers.overview": {
            "values": [
                "Key tracers in the NPZD cycle are phosphate, phytoplankton, zooplankton and detritus.  The growth of phytoplankton is limited when the iron tracer is low.  Oxygen and carbon cycles (carbonate, dissolved inorganic carbon and alkalinity) are coupled to the NPZD cycle within the ocean and exchange with the atmosphere.  A second natural dissolved inorganic carbon tracer is included, that exchanges with pre-industrical levels of atmospheric CO2. "
            ]
        }, 
        "cmip6.ocnbgchem.tracers.sulfur_cycle_present": {
            "values": [
                false
            ]
        }, 
        "cmip6.ocnbgchem.tracers.nutrients_present": {
            "values": [
                "Phosphorous (P)", 
                "Iron (Fe)"
            ]
        }, 
        "cmip6.ocnbgchem.tracers.ecosystem.phytoplankton.type": {
            "values": [
                "Generic"
            ]
        }, 
        "cmip6.ocnbgchem.tracers.ecosystem.zooplankton.type": {
            "values": [
                "Generic"
            ]
        }, 
        "cmip6.ocnbgchem.tracers.disolved_organic_matter.bacteria_present": {
            "values": [
                false
            ]
        }, 
        "cmip6.ocnbgchem.tracers.particules.method": {
            "values": [
                "Prognostic"
            ]
        }, 
        "cmip6.ocnbgchem.tracers.particules.types_if_prognostic": {
            "values": [
                "POC", 
                "PIC (aragonite"
            ]
        }, 
        "cmip6.ocnbgchem.tracers.particules.size_if_prognostic": {
            "values": [
                "No size spectrum used"
            ]
        }, 
        "cmip6.ocnbgchem.tracers.particules.sinking_speed_if_prognostic": {
            "values": [
                "Constant"
            ]
        }, 
        "cmip6.ocnbgchem.tracers.dic_alkalinity.abiotic_carbon": {
            "values": [
                false
            ]
        }, 
        "cmip6.ocnbgchem.tracers.dic_alkalinity.alkalinity": {
            "values": [
                "Prognostic"
            ]
        }
    }
}